cosmotalker/__init__.py
cosmotalker/api.py
cosmotalker/apod.py
cosmotalker/auto_installer.py
cosmotalker/celestial_knowledge.txt
cosmotalker/celestrak.py
cosmotalker/data.txt
cosmotalker/feedback.py
cosmotalker/get.py
cosmotalker/img.py
cosmotalker/info.py
cosmotalker/oolit.py
cosmotalker/search.py
cosmotalker/spacex.py
cosmotalker/ss.txt
cosmotalker/update.py
cosmotalker/wiki.py
cosmotalker-2.45.dist-info/METADATA
cosmotalker-2.45.dist-info/WHEEL
cosmotalker-2.45.dist-info/top_level.txt
cosmotalker-2.45.dist-info/RECORD
