Metadata-Version: 2.4
Name: cosmotalker
Version: 2.45
Summary: CosmoTalker is your gateway to the universe! Whether you're fascinated by stars, planets, or scientific phenomena, this tool brings the cosmos closer to you.
Home-page: https://github.com/bhuvanesh-m-dev/cosmotalker
Author: Bhuvanesh M
Author-email: bhuvaneshm.developer@gmail.com
Project-URL: Portfolio, https://bhuvaneshm.in
Project-URL: LinkedIn, https://www.linkedin.com/in/bhuvaneshm-developer
Project-URL: GitHub Repository, https://github.com/bhuvanesh-m-dev/cosmotalker
Classifier: Programming Language :: Python :: 3
Classifier: License :: OSI Approved :: MIT License
Classifier: Operating System :: OS Independent
Requires-Python: >=3.6
Dynamic: author
Dynamic: author-email
Dynamic: classifier
Dynamic: description
Dynamic: description-content-type
Dynamic: home-page
Dynamic: project-url
Dynamic: requires-python
Dynamic: summary
